project_goldberg_common/__init__.py
project_goldberg_common/math_module/__init__.py
project_goldberg_common/math_module/circle_module.py
project_goldberg_common/utils.py
project_goldberg_common-0.1.4.dist-info/WHEEL
project_goldberg_common-0.1.4.dist-info/METADATA
project_goldberg_common-0.1.4.dist-info/RECORD
