Metadata-Version: 2.1
Name: project-goldberg-common
Version: 0.1.4
Summary: 
License: MIT
Author: Simone Sangeniti
Author-email: snakenextgen@gmai.com
Requires-Python: >=3.10,<4.0
Classifier: License :: OSI Approved :: MIT License
Classifier: Programming Language :: Python :: 3
Classifier: Programming Language :: Python :: 3.10
Classifier: Programming Language :: Python :: 3.11
Requires-Dist: pytest (>=7.2.1,<8.0.0)
